Workbook

Sheet Indicadores
A1: Semana | B1: Fecha_fin | C1: Region | D1: Pedidos | E1: Ingresos_COP | F1: Entregas_a_tiempo_pct | G1: Devoluciones_pct | H1: No_conformidades_pct | I1: Tickets_soporte | J1: Backlog_pedidos | K1: Costo_logistico_COP | L1: Presupuesto_logistico_COP | M1: CSAT | N1: Tiempo_preparacion_min
A2: 1 | B2: 46178 | C2: Norte | D2: 1080 | E2: 162000000 | F2: 0.95 | G2: 0.032 | H2: 0.038 | I2: 74 | J2: 82 | K2: 27000000 | L2: 30000000 | M2: 89 | N2: 41
A3: 1 | B3: 46178 | C3: Centro | D3: 1220 | E3: 183000000 | F3: 0.95 | G3: 0.03 | H3: 0.035 | I3: 80 | J3: 88 | K3: 29200000 | L3: 32000000 | M3: 90 | N3: 40
A4: 1 | B4: 46178 | C4: Sur | D4: 980 | E4: 147000000 | F4: 0.94 | G4: 0.038 | H4: 0.041 | I4: 72 | J4: 80 | K4: 26000000 | L4: 29000000 | M4: 88 | N4: 41
A5: 1 | B5: 46178 | C5: Occidente | D5: 920 | E5: 138000000 | F5: 0.95 | G5: 0.031 | H5: 0.036 | I5: 65 | J5: 70 | K5: 24500000 | L5: 27000000 | M5: 90 | N5: 39
A6: 2 | B6: 46185 | C6: Norte | D6: 1160 | E6: 174000000 | F6: 0.95 | G6: 0.033 | H6: 0.039 | I6: 78 | J6: 86 | K6: 27600000 | L6: 30000000 | M6: 88 | N6: 42
A7: 2 | B7: 46185 | C7: Centro | D7: 1300 | E7: 195000000 | F7: 0.95 | G7: 0.031 | H7: 0.036 | I7: 85 | J7: 92 | K7: 30000000 | L7: 32000000 | M7: 89 | N7: 42
A8: 2 | B8: 46185 | C8: Sur | D8: 1040 | E8: 156000000 | F8: 0.94 | G8: 0.039 | H8: 0.042 | I8: 76 | J8: 84 | K8: 26700000 | L8: 29000000 | M8: 87 | N8: 42
A9: 2 | B9: 46185 | C9: Occidente | D9: 1000 | E9: 150000000 | F9: 0.95 | G9: 0.032 | H9: 0.037 | I9: 68 | J9: 72 | K9: 25000000 | L9: 27000000 | M9: 89 | N9: 40
A10: 3 | B10: 46192 | C10: Norte | D10: 1210 | E10: 181500000 | F10: 0.94 | G10: 0.035 | H10: 0.041 | I10: 86 | J10: 98 | K10: 28600000 | L10: 30000000 | M10: 87 | N10: 44
A11: 3 | B11: 46192 | C11: Centro | D11: 1390 | E11: 208500000 | F11: 0.94 | G11: 0.032 | H11: 0.038 | I11: 96 | J11: 106 | K11: 31200000 | L11: 32000000 | M11: 88 | N11: 45
A12: 3 | B12: 46192 | C12: Sur | D12: 1110 | E12: 166500000 | F12: 0.93 | G12: 0.041 | H12: 0.044 | I12: 88 | J12: 96 | K12: 27800000 | L12: 29000000 | M12: 86 | N12: 44
A13: 3 | B13: 46192 | C13: Occidente | D13: 1040 | E13: 156000000 | F13: 0.95 | G13: 0.032 | H13: 0.037 | I13: 72 | J13: 76 | K13: 25600000 | L13: 27000000 | M13: 89 | N13: 41
... A33: 8 | B33: 46227 | C33: Occidente | D33: 1315 | E33: 197250000 | F33: 0.94 | G33: 0.034 | H33: 0.04 | I33: 86 | J33: 85 | K33: 27400000 | L33: 27500000 | M33: 88 | N33: 46

Sheet Metas
A1: Indicador | B1: Meta | C1: Regla | D1: Unidad
A2: Entregas_a_tiempo_pct | B2: 0.93 | C2: Mayor o igual | D2: %
A3: Devoluciones_pct | B3: 0.045 | C3: Menor o igual | D3: %
A4: No_conformidades_pct | B4: 0.05 | C4: Menor o igual | D4: %
A5: Backlog_pedidos | B5: 120 | C5: Menor o igual | D5: Pedidos
A6: CSAT | B6: 85 | C6: Mayor o igual | D6: Puntos
A7: Tiempo_preparacion_min | B7: 50 | C7: Menor o igual | D7: Minutos
A8: Costo_logistico_COP | B8: Presupuesto_logistico_COP | C8: Menor o igual | D8: COP

Sheet Tecnologia
A1: Indicador | B1: Valor | C1: Unidad | D1: Interpretación
A2: Pedidos procesados en cuatro semanas | B2: 18460 | C2: Pedidos | D2: Base del análisis tecnológico
A3: Diferencias temporales de inventario | B3: 63 | C3: Casos | D3: Requiere monitoreo y procedimiento de contingencia
A4: Notificaciones duplicadas | B4: 27 | C4: Casos | D4: Ajuste de idempotencia en pruebas
A5: Umbral de alerta de sincronización | B5: 5 | C5: Minutos | D5: Generar alerta cuando la cola supere este tiempo
A6: Guardia técnica propuesta | B6: 07:00-21:00 | C6: Horario | D6: Primeros tres días de cada oleada

Sheet Presupuesto
A1: Concepto | B1: Importe_COP | C1: Estado | D1: Condición
A2: Presupuesto base disponible | B2: 27500000 | C2: Disponible | D2: Gastos asociados con actividad y responsable
A3: Ruta adicional de Logística Andina | B3: 18600000 | C3: Propuesta | D3: Adenda, pronóstico y aceptación antes del 30 de julio
A4: Monitoreo y guardia técnica | B4: 9800000 | C4: Estimación | D4: Validación de alcance y licencias temporales
A5: Adecuaciones operativas y staging | B5: 14200000 | C5: Estimación | D5: Evidencia por tienda y criterio de cierre
A6: Contingencia adicional máxima | B6: 20000000 | C6: Pendiente de aprobación | D6: Evidencia, cotización y aprobación conjunta
A8: Total de solicitudes estimadas | B8: =SUM(B3:B5) -> 42600000 | C8: Calculado
A9: Brecha frente al presupuesto base | B9: =MAX(0,B8-B2) -> 15100000 | C9: Calculado

Sheet Resumen
A1: Resumen de indicadores por región - última semana
A3: Región | B3: Entregas a tiempo | C3: Devoluciones | D3: No conformidades | E3: Backlog | F3: Costo logístico | G3: Presupuesto | H3: Variación costo | I3: CSAT | J3: Tiempo preparación | K3: Estado
A4: Norte | B4: =Indicadores!F30 -> 0.85 | C4: =Indicadores!G30 -> 0.044 | D4: =Indicadores!H30 -> 0.053 | E4: =Indicadores!J30 -> 280 | F4: =Indicadores!K30 -> 35600000 | G4: =Indicadores!L30 -> 30000000 | H4: =F4-G4 -> 5600000 | I4: =Indicadores!M30 -> 77 | J4: =Indicadores!N30 -> 57 | K4: =IF(OR(B4<0.9,C4>0.05,D4>0.05,E4>120,H4>0,I4<85,J4>50),"REQUIERE ATENCION","EN META") -> REQUIERE ATENCION
A5: Centro | B5: =Indicadores!F31 -> 0.92 | C5: =Indicadores!G31 -> 0.04 | D5: =Indicadores!H31 -> 0.048 | E5: =Indicadores!J31 -> 165 | F5: =Indicadores!K31 -> 35200000 | G5: =Indicadores!L31 -> 34000000 | H5: =F5-G5 -> 1200000 | I5: =Indicadores!M31 -> 83 | J5: =Indicadores!N31 -> 57 | K5: =IF(OR(B5<0.9,C5>0.05,D5>0.05,E5>120,H5>0,I5<85,J5>50),"REQUIERE ATENCION","EN META") -> REQUIERE ATENCION
A6: Sur | B6: =Indicadores!F32 -> 0.91 | C6: =Indicadores!G32 -> 0.055 | D6: =Indicadores!H32 -> 0.078 | E6: =Indicadores!J32 -> 150 | F6: =Indicadores!K32 -> 30500000 | G6: =Indicadores!L32 -> 29000000 | H6: =F6-G6 -> 1500000 | I6: =Indicadores!M32 -> 75 | J6: =Indicadores!N32 -> 54 | K6: =IF(OR(B6<0.9,C6>0.05,D6>0.05,E6>120,H6>0,I6<85,J6>50),"REQUIERE ATENCION","EN META") -> REQUIERE ATENCION
A7: Occidente | B7: =Indicadores!F33 -> 0.94 | C7: =Indicadores!G33 -> 0.034 | D7: =Indicadores!H33 -> 0.04 | E7: =Indicadores!J33 -> 85 | F7: =Indicadores!K33 -> 27400000 | G7: =Indicadores!L33 -> 27500000 | H7: =F7-G7 -> -100000 | I7: =Indicadores!M33 -> 88 | J7: =Indicadores!N33 -> 46 | K7: =IF(OR(B7<0.9,C7>0.05,D7>0.05,E7>120,H7>0,I7<85,J7>50),"REQUIERE ATENCION","EN META") -> EN META

Sheet _Grafico
A1: Semana | B1: Norte | C1: Centro | D1: Sur | E1: Occidente
A2: 1 | B2: =Indicadores!F2 -> 0.95 | C2: =Indicadores!F3 -> 0.95 | D2: =Indicadores!F4 -> 0.94 | E2: =Indicadores!F5 -> 0.95
A3: 2 | B3: =Indicadores!F6 -> 0.95 | C3: =Indicadores!F7 -> 0.95 | D3: =Indicadores!F8 -> 0.94 | E3: =Indicadores!F9 -> 0.95
A4: 3 | B4: =Indicadores!F10 -> 0.94 | C4: =Indicadores!F11 -> 0.94 | D4: =Indicadores!F12 -> 0.93 | E4: =Indicadores!F13 -> 0.95
A5: 4 | B5: =Indicadores!F14 -> 0.92 | C5: =Indicadores!F15 -> 0.94 | D5: =Indicadores!F16 -> 0.92 | E5: =Indicadores!F17 -> 0.94
A6: 5 | B6: =Indicadores!F18 -> 0.88 | C6: =Indicadores!F19 -> 0.93 | D6: =Indicadores!F20 -> 0.9 | E6: =Indicadores!F21 -> 0.94
A7: 6 | B7: =Indicadores!F22 -> 0.82 | C7: =Indicadores!F23 -> 0.92 | D7: =Indicadores!F24 -> 0.89 | E7: =Indicadores!F25 -> 0.94
A8: 7 | B8: =Indicadores!F26 -> 0.83 | C8: =Indicadores!F27 -> 0.92 | D8: =Indicadores!F28 -> 0.9 | E8: =Indicadores!F29 -> 0.94
A9: 8 | B9: =Indicadores!F30 -> 0.85 | C9: =Indicadores!F31 -> 0.92 | D9: =Indicadores!F32 -> 0.91 | E9: =Indicadores!F33 -> 0.94

Sheet Diccionario
A1: Caso ficticio: Comercializadora Valle Azul S.A.S. - Expansión Compra y Recoge
A2: Los importes se expresan en pesos colombianos (COP). Las posibles causas deben validarse con la reunión, Teams y la cadena de correos.
A3: Campo | B3: Descripción | C3: Tipo
A4: Semana | B4: Número consecutivo de semana analizada. | C4: Entero
A5: Fecha_fin | B5: Fecha de cierre de la semana. | C5: Fecha
A6: Region | B6: Norte, Centro, Sur u Occidente. | C6: Texto
A7: Pedidos | B7: Pedidos procesados. | C7: Entero
A8: Ingresos_COP | B8: Ingresos semanales ficticios. | C8: Moneda COP
A9: Entregas_a_tiempo_pct | B9: Proporción entregada dentro del compromiso. | C9: Porcentaje
A10: Devoluciones_pct | B10: Proporción de pedidos devueltos. | C10: Porcentaje
A11: No_conformidades_pct | B11: Proporción con fallas de preparación, empaque, rotulado o contenido. | C11: Porcentaje
A12: Tickets_soporte | B12: Casos de soporte. | C12: Entero
A13: Backlog_pedidos | B13: Pedidos abiertos al cierre. | C13: Entero
A14: Costo_logistico_COP | B14: Costo logístico real. | C14: Moneda COP
... A17: Tiempo_preparacion_min | B17: Tiempo promedio de preparación por pedido. | C17: Entero
